nomad_parser_wannier90/__init__.py
nomad_parser_wannier90/_version.py
nomad_parser_wannier90/parsers/__init__.py
nomad_parser_wannier90/parsers/band_parser.py
nomad_parser_wannier90/parsers/dos_parser.py
nomad_parser_wannier90/parsers/hr_parser.py
nomad_parser_wannier90/parsers/parser.py
nomad_parser_wannier90/parsers/win_parser.py
nomad_parser_wannier90/parsers/utils/__init__.py
nomad_parser_wannier90/parsers/utils/utils.py
nomad_parser_wannier90/schema_packages/__init__.py
nomad_parser_wannier90/schema_packages/package.py
nomad_parser_wannier90-0.0.0.dist-info/LICENSE
nomad_parser_wannier90-0.0.0.dist-info/METADATA
nomad_parser_wannier90-0.0.0.dist-info/WHEEL
nomad_parser_wannier90-0.0.0.dist-info/entry_points.txt
nomad_parser_wannier90-0.0.0.dist-info/top_level.txt
nomad_parser_wannier90-0.0.0.dist-info/RECORD
