Metadata-Version: 2.1
Name: nomad-parser-wannier90
Version: 0.0.0
Summary: A NOMAD parser plugin for Wannier90 input/output files.
Author-email: "Jose M. Pizarro" <jose.pizarro@physik.hu-berlin.de>
Maintainer-email: "Jose M. Pizarro" <jose.pizarro@physik.hu-berlin.de>
License: 
Project-URL: Homepage, https://github.com/FAIRmat-NFDI/nomad-parser-wannier90
Project-URL: Bug Tracker, https://github.com/FAIRmat-NFDI/nomad-parser-wannier90/issues
Project-URL: Documentation, https://FAIRmat-NFDI.github.io/nomad-parser-wannier90/
Classifier: Intended Audience :: Developers
Classifier: Operating System :: OS Independent
Classifier: Programming Language :: Python
Classifier: Programming Language :: Python :: 3.9
Classifier: License :: OSI Approved :: Apache Software License
Requires-Python: >=3.9
License-File: LICENSE
Requires-Dist: nomad-lab >=1.3.0
Requires-Dist: nomad-simulations >=0.0.2
Provides-Extra: dev
Requires-Dist: mypy ==1.0.1 ; extra == 'dev'
Requires-Dist: ruff ; extra == 'dev'
Requires-Dist: pytest ; extra == 'dev'
Requires-Dist: pytest-timeout ; extra == 'dev'
Requires-Dist: pytest-cov ; extra == 'dev'
Requires-Dist: structlog ; extra == 'dev'
